uptycs_py/__init__.py
uptycs_py/upt_api.py
uptycs_py-0.0.3.dist-info/LICENSE
uptycs_py-0.0.3.dist-info/METADATA
uptycs_py-0.0.3.dist-info/WHEEL
uptycs_py-0.0.3.dist-info/top_level.txt
uptycs_py-0.0.3.dist-info/RECORD
