Metadata-Version: 2.1
Name: uptycs-py
Version: 0.0.3
Summary: Uptycs API helper library (for Python 3)
Home-page: https://github.com/Uptycs/uptycs-py
Author: Julian Wayte
Author-email: Julian Wayte <jwayte@uptycs.com>, Serge Teren <steren@uptycs.com>
Maintainer-email: Chandrasekhar <cgadde@uptycs.com>, Alan Koshy <akoshy@uptycs.com>
License: MIT License        
Project-URL: Homepage, https://github.com/pypa/uptycs_py
Project-URL: Bug Tracker, https://github.com/pypa/uptycs-py/issues
Classifier: Programming Language :: Python :: 3
Classifier: Operating System :: OS Independent
Requires-Python: >=3.7
License-File: LICENSE
Requires-Dist: requests
Requires-Dist: PyJWT (>=0.5.2)
